{"nodes": [{"id": "c_striver_website_striver_web_src_components_discover_discover_js", "label": "Discover.js", "file_type": "code", "source_file": "C:\\Striver_Website\\striver-web\\src\\components\\Discover\\Discover.js", "source_location": "L1"}, {"id": "discover_discover_nav_items", "label": "NAV_ITEMS", "file_type": "code", "source_file": "C:\\Striver_Website\\striver-web\\src\\components\\Discover\\Discover.js", "source_location": "L12"}, {"id": "discover_discover_discover", "label": "Discover()", "file_type": "code", "source_file": "C:\\Striver_Website\\striver-web\\src\\components\\Discover\\Discover.js", "source_location": "L14"}], "edges": [{"source": "c_striver_website_striver_web_src_components_discover_discover_js", "target": "react", "relation": "imports_from", "context": "import", "confidence": "EXTRACTED", "source_file": "C:\\Striver_Website\\striver-web\\src\\components\\Discover\\Discover.js", "source_location": "L3", "weight": 1.0}, {"source": "c_striver_website_striver_web_src_components_discover_discover_js", "target": "image", "relation": "imports_from", "context": "import", "confidence": "EXTRACTED", "source_file": "C:\\Striver_Website\\striver-web\\src\\components\\Discover\\Discover.js", "source_location": "L4", "weight": 1.0}, {"source": "c_striver_website_striver_web_src_components_discover_discover_js", "target": "link", "relation": "imports_from", "context": "import", "confidence": "EXTRACTED", "source_file": "C:\\Striver_Website\\striver-web\\src\\components\\Discover\\Discover.js", "source_location": "L5", "weight": 1.0}, {"source": "c_striver_website_striver_web_src_components_discover_discover_js", "target": "gsap", "relation": "imports_from", "context": "import", "confidence": "EXTRACTED", "source_file": "C:\\Striver_Website\\striver-web\\src\\components\\Discover\\Discover.js", "source_location": "L6", "weight": 1.0}, {"source": "c_striver_website_striver_web_src_components_discover_discover_js", "target": "scrolltrigger", "relation": "imports_from", "context": "import", "confidence": "EXTRACTED", "source_file": "C:\\Striver_Website\\striver-web\\src\\components\\Discover\\Discover.js", "source_location": "L7", "weight": 1.0}, {"source": "c_striver_website_striver_web_src_components_discover_discover_js", "target": "c_striver_website_striver_web_src_components_discover_discover_module_css", "relation": "imports_from", "context": "import", "confidence": "EXTRACTED", "source_file": "C:\\Striver_Website\\striver-web\\src\\components\\Discover\\Discover.js", "source_location": "L8", "weight": 1.0}, {"source": "c_striver_website_striver_web_src_components_discover_discover_js", "target": "discover_discover_nav_items", "relation": "contains", "confidence": "EXTRACTED", "source_file": "C:\\Striver_Website\\striver-web\\src\\components\\Discover\\Discover.js", "source_location": "L12", "weight": 1.0}, {"source": "c_striver_website_striver_web_src_components_discover_discover_js", "target": "discover_discover_discover", "relation": "contains", "confidence": "EXTRACTED", "source_file": "C:\\Striver_Website\\striver-web\\src\\components\\Discover\\Discover.js", "source_location": "L14", "weight": 1.0}], "raw_calls": [{"caller_nid": "discover_discover_discover", "callee": "useState", "is_member_call": false, "source_file": "C:\\Striver_Website\\striver-web\\src\\components\\Discover\\Discover.js", "source_location": "L15"}, {"caller_nid": "discover_discover_discover", "callee": "useRef", "is_member_call": false, "source_file": "C:\\Striver_Website\\striver-web\\src\\components\\Discover\\Discover.js", "source_location": "L16"}, {"caller_nid": "discover_discover_discover", "callee": "useRef", "is_member_call": false, "source_file": "C:\\Striver_Website\\striver-web\\src\\components\\Discover\\Discover.js", "source_location": "L17"}, {"caller_nid": "discover_discover_discover", "callee": "useRef", "is_member_call": false, "source_file": "C:\\Striver_Website\\striver-web\\src\\components\\Discover\\Discover.js", "source_location": "L18"}, {"caller_nid": "discover_discover_discover", "callee": "useRef", "is_member_call": false, "source_file": "C:\\Striver_Website\\striver-web\\src\\components\\Discover\\Discover.js", "source_location": "L19"}, {"caller_nid": "discover_discover_discover", "callee": "useRef", "is_member_call": false, "source_file": "C:\\Striver_Website\\striver-web\\src\\components\\Discover\\Discover.js", "source_location": "L20"}, {"caller_nid": "discover_discover_discover", "callee": "useEffect", "is_member_call": false, "source_file": "C:\\Striver_Website\\striver-web\\src\\components\\Discover\\Discover.js", "source_location": "L22"}]}