{"nodes": [{"id": "c_striver_website_striver_web_src_app_home_page_js", "label": "page.js", "file_type": "code", "source_file": "C:\\Striver_Website\\striver-web\\src\\app\\home\\page.js", "source_location": "L1"}, {"id": "home_page_metadata", "label": "metadata", "file_type": "code", "source_file": "C:\\Striver_Website\\striver-web\\src\\app\\home\\page.js", "source_location": "L3"}, {"id": "home_page_homeenvironment", "label": "HomeEnvironment()", "file_type": "code", "source_file": "C:\\Striver_Website\\striver-web\\src\\app\\home\\page.js", "source_location": "L8"}], "edges": [{"source": "c_striver_website_striver_web_src_app_home_page_js", "target": "environmentpage", "relation": "imports_from", "context": "import", "confidence": "EXTRACTED", "source_file": "C:\\Striver_Website\\striver-web\\src\\app\\home\\page.js", "source_location": "L1", "weight": 1.0}, {"source": "c_striver_website_striver_web_src_app_home_page_js", "target": "home_page_metadata", "relation": "contains", "confidence": "EXTRACTED", "source_file": "C:\\Striver_Website\\striver-web\\src\\app\\home\\page.js", "source_location": "L3", "weight": 1.0}, {"source": "c_striver_website_striver_web_src_app_home_page_js", "target": "home_page_homeenvironment", "relation": "contains", "confidence": "EXTRACTED", "source_file": "C:\\Striver_Website\\striver-web\\src\\app\\home\\page.js", "source_location": "L8", "weight": 1.0}], "raw_calls": []}